Foldpro/FoldproHelpers.py
Foldpro/Foldpro_command.py
Foldpro/__init__.py
Foldpro/main.py
Foldpro/overall_flow.py
Foldpro/preflight_operations.py
foldpro-1.0.2.dist-info/entry_points.txt
foldpro-1.0.2.dist-info/licenses/LICENSE
foldpro-1.0.2.dist-info/WHEEL
foldpro-1.0.2.dist-info/METADATA
foldpro-1.0.2.dist-info/RECORD
