Metadata-Version: 2.4
Name: Foldpro
Version: 1.0.2
Summary: A program to make organized copies of your folders.
Keywords: folders,organization,macOS
Author-email: Iman Taeb <imantaeb507@gmail.com>
Requires-Python: >=3.9
Classifier: Programming Language :: Python :: 3
Classifier: Operating System :: MacOS
License-File: LICENSE
Requires-Dist: rich>=14.2.0
